eopsin/__init__.py
eopsin/__main__.py
eopsin/compiler.py
eopsin/ledger/__init__.py
eopsin/ledger/interval.py
eopsin/optimize/__init__.py
eopsin/optimize/optimize_remove_deadvars.py
eopsin/optimize/optimize_remove_pass.py
eopsin/optimize/optimize_varlen.py
eopsin/prelude.py
eopsin/rewrite/__init__.py
eopsin/rewrite/rewrite_augassign.py
eopsin/rewrite/rewrite_forbidden_overwrites.py
eopsin/rewrite/rewrite_import.py
eopsin/rewrite/rewrite_import_dataclasses.py
eopsin/rewrite/rewrite_import_hashlib.py
eopsin/rewrite/rewrite_import_plutusdata.py
eopsin/rewrite/rewrite_import_typing.py
eopsin/rewrite/rewrite_inject_builtin_constr.py
eopsin/rewrite/rewrite_inject_builtins.py
eopsin/rewrite/rewrite_remove_type_stuff.py
eopsin/rewrite/rewrite_tuple_assign.py
eopsin/tests/__init__.py
eopsin/tests/test_builtins.py
eopsin/tests/test_ledger/__init__.py
eopsin/tests/test_ledger/test_interval.py
eopsin/tests/test_misc.py
eopsin/tests/test_ops.py
eopsin/tests/test_stdlib.py
eopsin/type_inference.py
eopsin/typed_ast.py
eopsin/util.py
eopsin_lang-0.9.12.dist-info/LICENSE.txt
eopsin_lang-0.9.12.dist-info/METADATA
eopsin_lang-0.9.12.dist-info/WHEEL
eopsin_lang-0.9.12.dist-info/entry_points.txt
eopsin_lang-0.9.12.dist-info/RECORD
