Metadata-Version: 2.1
Name: eopsin-lang
Version: 0.9.12
Summary: A simple pythonic programming language for Smart Contracts on Cardano
Home-page: https://github.com/opshin/eopsin
License: MIT
Keywords: python,language,programming-language,compiler,validator,smart-contracts,cardano
Author: nielstron
Author-email: n.muendler@web.de
Requires-Python: >=3.8,<3.9
Classifier: Development Status :: 3 - Alpha
Classifier: Intended Audience :: Developers
Classifier: License :: OSI Approved :: MIT License
Classifier: Programming Language :: Python :: 3
Classifier: Programming Language :: Python :: 3.8
Classifier: Programming Language :: Python :: 3.8
Classifier: Topic :: Software Development :: Compilers
Requires-Dist: frozenlist (==1.3.3)
Requires-Dist: pluthon (==0.3.1)
Requires-Dist: pyaiken (==0.4.0)
Requires-Dist: pycardano (==0.7.2)
Requires-Dist: uplc (==0.5.6)
Project-URL: Documentation, https://eopsin.opshin.dev/
Project-URL: Repository, https://github.com/opshin/eopsin
